dws/__init__.py
dws/app/__init__.py
dws/app/logs.py
dws/app/cli/__init__.py
dws/app/cli/dws.py
dws/app/cli/commands/__init__.py
dws/app/cli/commands/version.py
dws/app/cli/commands/did/__init__.py
dws/app/cli/commands/did/keri/__init__.py
dws/app/cli/commands/did/keri/resolve.py
dws/app/cli/commands/did/keri/resolver-service.py
dws/app/cli/commands/did/webs/__init__.py
dws/app/cli/commands/did/webs/generate.py
dws/app/cli/commands/did/webs/resolve.py
dws/app/cli/commands/did/webs/resolver-service.py
dws/app/cli/commands/did/webs/service.py
dws/core/__init__.py
dws/core/artifacting.py
dws/core/didding.py
dws/core/didkeri.py
dws/core/generating.py
dws/core/habs.py
dws/core/oobiing.py
dws/core/requesting.py
dws/core/resolving.py
dws/core/webbing.py
dws/core/ends/__init__.py
dws/core/ends/did_webs_resource_end.py
dws/core/ends/keri_cesr_resource_end.py
dws/core/ends/monitoring.py
dws/didcomm/__init__.py
dws/didcomm/hello-world.py
dws/didcomm/utils.py
did_webs_resolver-0.3.3.dist-info/METADATA
did_webs_resolver-0.3.3.dist-info/WHEEL
did_webs_resolver-0.3.3.dist-info/entry_points.txt
did_webs_resolver-0.3.3.dist-info/licenses/LICENSE
did_webs_resolver-0.3.3.dist-info/RECORD
