Metadata-Version: 2.4
Name: did-webs-resolver
Version: 0.3.3
Summary: did:webs DID Method Resolver
Project-URL: Documentation, https://github.com/GLEIF-IT/did-webs-resolver/docs
Project-URL: Changelog, https://github.com/GLEIF-IT/did-webs-resolver/CHANGELOG.md
Project-URL: Issue Tracker, https://github.com/GLEIF-IT/did-webs-resolver/issues
Author-email: "Philip S. Feairheller" <pfeairheller@gmail.com>, "Kent O. P. Bull" <kent@kentbull.com>
License: Apache Software License 2.0
License-File: LICENSE
Keywords: acdc,cesr,did,did:webs,keri,resolver,vlei,webs
Requires-Python: >=3.12.6
Requires-Dist: falcon<4.3.0,>=4.0.2
Requires-Dist: keri<1.3.0,>=1.2.7
Requires-Dist: multicommand<2.0.2,>=1.0.0
Requires-Dist: requests>=2.32.4
Requires-Dist: vgate>=0.1.4
